[{"playlist":"Third Gen Fall 2014","title":"MK Third Gen Fall 2014: Annabelle","unique_id":"85O8OALDFR8","uploaded_at":"2014-10-24T07:03:36Z"},{"playlist":"Third Gen Fall 2014","title":"CS 3rd Gen Fall 2014","unique_id":"ZrvHrcAmI_8","uploaded_at":"2014-10-23T16:36:18Z"},{"playlist":"Third Gen Fall 2014","title":"SO Third Gen Fall 2014: House 13","unique_id":"vKSlpEjd7H8","uploaded_at":"2014-10-23T16:35:35Z"},{"playlist":"Third Gen Fall 2014","title":"HT Third Gen Fall 2014: Historians Best Committee","unique_id":"W0xS1OJp2es","uploaded_at":"2014-10-24T06:51:55Z"},{"playlist":"Third Gen Fall 2014","title":"PD Third Gen: Fall 2014","unique_id":"B26YQxoW0mw","uploaded_at":"2014-10-23T21:22:27Z"},{"playlist":"Third Gen Fall 2014","title":"CO Third Gen Fall 2014: League of Benders","unique_id":"vFxd8kaykr0","uploaded_at":"2014-10-24T06:42:50Z"},{"playlist":"Third Gen Fall 2014","title":"PB Third Gen: Fall 2014","unique_id":"Ixc1Ft9PYAw","uploaded_at":"2014-10-24T07:07:31Z"},{"playlist":"Third Gen Fall 2014","title":"EX Third Gen Fall 2014: Gossip Girl","unique_id":"GCF_yiRRYn8","uploaded_at":"2014-10-23T19:49:41Z"},{"playlist":"Third Gen Fall 2014","title":"FI Third Gen: Fall 2014","unique_id":"ZMVF6rLttbg","uploaded_at":"2014-10-24T02:34:25Z"},{"playlist":"Third Gen Fall 2014","title":"IN Third Gen: Fall 2014","unique_id":"SV7VbX_P9Pk","uploaded_at":"2014-10-23T18:29:44Z"},{"playlist":"Third Gen Fall 2014","title":"Third Gen Fall 2014: Bloopers","unique_id":"CNyMqEJ4ZOw","uploaded_at":"2014-10-24T06:56:42Z"},{"playlist":"PBLtv Season 9","title":"PBLtv S9E1 - lambda beta phi files","unique_id":"gx2Jmwl7gOs","uploaded_at":"2014-10-12T04:38:34Z"},{"playlist":"PBLtv Season 9","title":"PBLtv S9E3 - Three Types of Best Friends","unique_id":"mK5W-uKJb1I","uploaded_at":"2014-10-12T05:45:28Z"},{"playlist":"PBLtv Season 9","title":"PBL TV Season 9 Episode 2: \"Daily Inconveniences\"","unique_id":"zF9uQlk3yXU","uploaded_at":"2014-10-12T06:05:29Z"},{"playlist":"PBLtv Season 9","title":"PBLtv S9E4 - PBL Cribz","unique_id":"DxI8COmUlpw","uploaded_at":"2014-10-12T05:15:59Z"},{"playlist":"Fall 2014","title":"[Fall 2014] Mr PBL","unique_id":"XirbK8qjS4g","uploaded_at":"2014-10-01T07:24:12Z"},{"playlist":"Fall 2014","title":"[IN] Assassins Trailer","unique_id":"sCvozKPqv-o","uploaded_at":"2014-10-01T08:24:51Z"},{"playlist":"Fall 2014","title":"PBLtv S9E1 - lambda beta phi files","unique_id":"gx2Jmwl7gOs","uploaded_at":"2014-10-12T04:38:34Z"},{"playlist":"PBL Apprentice | Fall 2014","title":"[IN] The Apprentice - Professional Development (Fall 2014)","unique_id":"m6giNOV0s9c","uploaded_at":"2014-09-23T06:41:46Z"},{"playlist":"PBL Apprentice | Fall 2014","title":"[IN] The Apprentice - Executives (Fall 2014)","unique_id":"yi61lvRJcRA","uploaded_at":"2014-09-27T03:42:34Z"},{"playlist":"PBL Apprentice | Fall 2014","title":"[IN] The Apprentice - Publications (Fall 2014)","unique_id":"ZJOwg5D_jyY","uploaded_at":"2014-10-02T01:39:27Z"},{"playlist":"PBL Apprentice | Fall 2014","title":"[IN] The Apprentice - Community Service (Fall 2014)","unique_id":"O9kpVN9Yx5w","uploaded_at":"2014-10-06T00:54:31Z"},{"playlist":"PBL Apprentice | Fall 2014","title":"[IN] The Apprentice - Consulting (Fall 2014)","unique_id":"qAdAaue_my4","uploaded_at":"2014-10-10T06:47:07Z"},{"playlist":"PBL Apprentice | Fall 2014","title":"[IN] The Apprentice - Historians (Fall 2014)","unique_id":"WsCbIPPNhwE","uploaded_at":"2014-10-22T22:55:12Z"},{"playlist":"Fall 2011","title":"[PBL] Publications Fall 2011 Banquet Video","unique_id":"6TNGC-mxbEA","uploaded_at":"2012-03-13T10:12:25Z"},{"playlist":"Fall 2011","title":"[PBL] Historian 2011 Fall Banquet Video.avi","unique_id":"GvS9pWjUYiA","uploaded_at":"2012-02-27T05:01:51Z"},{"playlist":"Fall 2011","title":"[PBL] Finance Fall 2011 Banquet.avi","unique_id":"shhuHvZX428","uploaded_at":"2012-02-21T05:30:47Z"},{"playlist":"Fall 2011","title":"[PBL] Exec Video Fall Banquet Video","unique_id":"N8UROqGBsik","uploaded_at":"2012-02-11T03:19:53Z"},{"playlist":"Fall 2011","title":"[PBL] Consulting Fall 2011 Banquet Video","unique_id":"EPxfTRWAT0w","uploaded_at":"2012-02-10T23:38:43Z"},{"playlist":"Fall 2011","title":"[PBL] Social - Banquet Video Fall 2011 - Sunset Blvd","unique_id":"JPgYW96-VQo","uploaded_at":"2011-12-11T01:43:24Z"},{"playlist":"Fall 2011","title":"[PBL] Community Service - Fall 2011 Banquet Video","unique_id":"sX0AADLn1FM","uploaded_at":"2011-12-10T21:03:37Z"},{"playlist":"Fall 2011","title":"[PBL] Marketing - Fall 2011 Banquet Video","unique_id":"oAO1PsjAIaY","uploaded_at":"2011-12-08T02:31:11Z"},{"playlist":"Fall 2011","title":"PBLtv Season 3 Episode 7","unique_id":"Zvulz-aZzbM","uploaded_at":"2011-11-30T03:36:00Z"},{"playlist":"Fall 2011","title":"PBLtv Season 3 Episode 6","unique_id":"tAVJZ7iZq8Y","uploaded_at":"2011-11-19T16:34:01Z"},{"playlist":"Fall 2011","title":"PBLtv Season 3 Episode 5","unique_id":"JERwFH3DQuk","uploaded_at":"2011-11-15T16:21:52Z"},{"playlist":"Fall 2011","title":"Fall 2011 PBL's Got Talent: Publications","unique_id":"GEiZT6M4u-s","uploaded_at":"2011-11-08T00:20:34Z"},{"playlist":"Fall 2011","title":"Fall 2011 PBL's Got Talent: Professional Development","unique_id":"tauwR-PwFX8","uploaded_at":"2011-11-07T22:33:57Z"},{"playlist":"Fall 2011","title":"Fall 2011 PBL's Got Talent: Marketing","unique_id":"hg33U6OP8M8","uploaded_at":"2011-11-07T21:01:03Z"},{"playlist":"Fall 2011","title":"Fall 2011 PBL's Got Talent: Historian","unique_id":"0XW8n-RYJJI","uploaded_at":"2011-11-07T19:41:04Z"},{"playlist":"Fall 2011","title":"Fall 2011 PBL's Got Talent: Faculty Relations","unique_id":"WYKt-fidfYU","uploaded_at":"2011-11-07T18:34:18Z"},{"playlist":"Fall 2011","title":"Fall 2011 PBL's Got Talent: Finance","unique_id":"HThSlceHW3I","uploaded_at":"2011-11-07T17:15:54Z"},{"playlist":"Fall 2011","title":"Fall 2011 PBL's Got Talent: Execs","unique_id":"lrbPDpDnZeg","uploaded_at":"2011-11-07T15:23:09Z"},{"playlist":"Fall 2011","title":"Fall 2011 PBL's Got Talent: Community Service","unique_id":"GP8u3pDkleY","uploaded_at":"2011-11-07T14:38:16Z"},{"playlist":"Fall 2011","title":"Fall 2011 PBL's Got Talent: Consulting","unique_id":"T4pYkHpoWEo","uploaded_at":"2011-11-07T13:31:13Z"},{"playlist":"Fall 2011","title":"Fall 2011 PBL's Got Talent: Brian and Yun","unique_id":"RKGK6zypHQ0","uploaded_at":"2011-11-07T12:26:14Z"},{"playlist":"Fall 2011","title":"PBLtv Season 3 Episode 4","unique_id":"DH-dmYnrT3E","uploaded_at":"2011-11-01T07:10:29Z"},{"playlist":"Fall 2011","title":"PBLtv Season 3 Episode 3","unique_id":"vMB5PHS-DvY","uploaded_at":"2011-10-22T18:42:30Z"},{"playlist":"Fall 2011","title":"PBLtv Season 3 Episode 2","unique_id":"tCw4jUsCxSM","uploaded_at":"2011-10-16T05:04:42Z"},{"playlist":"Fall 2011","title":"Mr. PBL Berkeley 2011","unique_id":"tHZiaFJ8sb0","uploaded_at":"2011-10-14T05:10:17Z"},{"playlist":"Spring 2012","title":"PBL Spring 2012 Officers Introduction","unique_id":"gQ__BeGhU1Y","uploaded_at":"2012-02-06T22:57:18Z"},{"playlist":"Spring 2012","title":"[HT] Spring 2012 3rd Gen - Finding Dreams","unique_id":"cai7_R4GBwQ","uploaded_at":"2012-04-11T19:38:01Z"},{"playlist":"Spring 2012","title":"[PBL] Faculty Relations Banquet Spring 2012","unique_id":"oM1t2dQ7T-E","uploaded_at":"2012-05-01T12:42:26Z"},{"playlist":"Spring 2012","title":"[PBL] Historian Banquet Spring 2012","unique_id":"aUfsjX0MGuA","uploaded_at":"2012-05-01T20:45:58Z"},{"playlist":"Spring 2012","title":"PBLtv S4E6","unique_id":"rO1PMvnACLs","uploaded_at":"2012-05-01T22:23:32Z"},{"playlist":"Spring 2012","title":"[PBL] Publications Banquet Spring 2012","unique_id":"Ss7-8mpBiOU","uploaded_at":"2012-05-01T18:09:50Z"},{"playlist":"Spring 2012","title":"[PBL] Professional Development Banquet Spring 2012","unique_id":"9KJLkei7PAY","uploaded_at":"2012-05-01T16:24:29Z"},{"playlist":"Spring 2012","title":"[PBL] Marketing Banquet Spring 2012","unique_id":"Xk-ElmRX8l0","uploaded_at":"2012-05-01T16:02:15Z"},{"playlist":"Spring 2012","title":"[PBL] Internal Networking Banquet Spring 2012","unique_id":"LoRtChwFi5c","uploaded_at":"2012-05-01T13:54:02Z"},{"playlist":"Spring 2012","title":"[PBL] Finance Banquet Spring 2012","unique_id":"iJVsfd77JBg","uploaded_at":"2012-05-01T11:00:43Z"},{"playlist":"Spring 2012","title":"[PBL] Exec Banquet Spring 2012","unique_id":"q2cbcD1nnwY","uploaded_at":"2012-05-01T10:47:34Z"},{"playlist":"Spring 2012","title":"[PBL] Community Service Banquet Spring 2012","unique_id":"Mig2a5kqdus","uploaded_at":"2012-05-01T09:21:44Z"},{"playlist":"Spring 2012","title":"[PBL] Consulting Banquet Spring 2012","unique_id":"EDVWCHLHDWc","uploaded_at":"2012-05-01T06:27:30Z"},{"playlist":"Spring 2012","title":"PBLtv S4E4","unique_id":"5v27kRRKHAA","uploaded_at":"2012-04-18T13:03:45Z"},{"playlist":"Spring 2012","title":"PBLtv S4E5","unique_id":"WpDGnrEi6NM","uploaded_at":"2012-04-27T17:58:16Z"},{"playlist":"Spring 2012","title":"PBLtv S4E3","unique_id":"fM0i7o7WNOg","uploaded_at":"2012-03-23T20:19:07Z"},{"playlist":"Spring 2012","title":"PBLtv S4E2","unique_id":"OW4MUO5VtQw","uploaded_at":"2012-03-19T21:44:05Z"},{"playlist":"Spring 2012","title":"PBLtv S4E1","unique_id":"hWxNaRIVY8w","uploaded_at":"2012-03-12T11:05:35Z"},{"playlist":"Spring 2012","title":"IN Assassins Defense","unique_id":"Jzvrj06V9Bw","uploaded_at":"2012-03-06T04:07:04Z"},{"playlist":"Spring 2014 Banquet Videos","title":"Banquet Spring 2014: Internal Networking","unique_id":"2Ir5q88ePBc","uploaded_at":"2014-05-06T00:02:45Z"},{"playlist":"Spring 2014 Banquet Videos","title":"Banquet Spring 2014: Marketing","unique_id":"S-neWHcbrbs","uploaded_at":"2014-05-06T00:03:33Z"},{"playlist":"Spring 2014 Banquet Videos","title":"Historian Banquet Video Spring 2014","unique_id":"uhagioKYKko","uploaded_at":"2014-05-06T00:44:39Z"},{"playlist":"Spring 2014 Banquet Videos","title":"[FI] Spring 2014 Banquet Video","unique_id":"zm3Z4sw5pH0","uploaded_at":"2014-05-07T04:22:55Z"},{"playlist":"Spring 2014 Banquet Videos","title":"CO Banquet Video Spring 2014","unique_id":"bdJVYCqkzp0","uploaded_at":"2014-05-06T03:27:38Z"},{"playlist":"3rd Gen | Spring 2014","title":"[PBL] Third General Meeting Spring 2014: Marketing","unique_id":"uBbSFjw-qgs","uploaded_at":"2014-04-04T17:40:38Z"},{"playlist":"3rd Gen | Spring 2014","title":"[PBL] Third General Meeting Spring 2014: Publications","unique_id":"KXFl6gP-cGk","uploaded_at":"2014-04-04T17:55:10Z"},{"playlist":"3rd Gen | Spring 2014","title":"[PBL] Third General Meeting Spring 2014: Internal Networking","unique_id":"Rk_1tmOHG0c","uploaded_at":"2014-04-05T03:51:17Z"},{"playlist":"3rd Gen | Spring 2014","title":"[PBL] Third General Meeting Spring 2014: BLOOPERS","unique_id":"uZI66OUuTiM","uploaded_at":"2014-04-07T00:41:12Z"},{"playlist":"3rd Gen | Spring 2014","title":"PBLTV Season 8 | I Had an Interview","unique_id":"w2PQuvMvL6E","uploaded_at":"2014-04-04T17:16:03Z"},{"playlist":"3rd Gen | Spring 2014","title":"[PBL] Third General Meeting Spring 2014: Finance","unique_id":"8EoozLBqw44","uploaded_at":"2014-04-07T00:40:31Z"},{"playlist":"3rd Gen | Spring 2014","title":"[PBL] Third General Meeting Spring 2014: Social","unique_id":"9qB-TWdOLEc","uploaded_at":"2014-04-07T01:22:09Z"},{"playlist":"PBL TV Season 8 | Spring 2014","title":"PBLTV Season 8 | Episode 1 - The Vice","unique_id":"tDL-XJ6KHms","uploaded_at":"2014-03-03T23:44:07Z"},{"playlist":"PBL TV Season 8 | Spring 2014","title":"PBLTV Season 8 | Episode 2 - Valentine","unique_id":"iB3xs0r0Kqo","uploaded_at":"2014-03-06T02:56:31Z"},{"playlist":"PBL TV Season 8 | Spring 2014","title":"PBL TV Season 8 | Episode 3 - Cycles","unique_id":"t5yIOIg_c90","uploaded_at":"2014-03-07T10:12:39Z"},{"playlist":"PBL TV Season 8 | Spring 2014","title":"PBL TV Season 8 | Episode 4 - Prom. Prom? Prom!","unique_id":"XvVFlK39WFA","uploaded_at":"2014-04-11T07:46:05Z"},{"playlist":"PBL TV Season 8 | Spring 2014","title":"PBLTV Season 8 | Episode 5 - Haru Haru","unique_id":"J7rEh9KyRTs","uploaded_at":"2014-04-26T16:38:18Z"},{"playlist":"PBL Apprentice | Spring 2014","title":"[IN] The Apprentice - Finance, Part 1 (Spring 2014)","unique_id":"5W3UT-DX9Cg","uploaded_at":"2014-03-04T07:00:01Z"},{"playlist":"PBL Apprentice | Spring 2014","title":"[IN] The Apprentice - Publications (Spring 2014)","unique_id":"teM2UWX-xE4","uploaded_at":"2014-03-04T06:28:52Z"},{"playlist":"PBL Apprentice | Spring 2014","title":"[IN] The Apprentice - Professional Development (Spring 2014)","unique_id":"_LPHJ9nmTEk","uploaded_at":"2014-03-07T07:51:45Z"},{"playlist":"PBL Apprentice | Spring 2014","title":"[IN] The Apprentice - Community Service (Spring 2014)","unique_id":"A4feaftnz44","uploaded_at":"2014-03-10T01:09:12Z"},{"playlist":"PBL Apprentice | Spring 2014","title":"[IN] The Apprentice - Historians (Spring 2014)","unique_id":"o_FhTNSTZAg","uploaded_at":"2014-03-27T03:53:35Z"},{"playlist":"PBL Apprentice | Spring 2014","title":"[IN] The Apprentice - Internal Networking (Spring 2014)","unique_id":"qKndT4WH_OI","uploaded_at":"2014-04-08T06:36:22Z"},{"playlist":"PBL Apprentice | Spring 2014","title":"[IN] The Apprentice - Social (Spring 2014)","unique_id":"8O9CrWwY6Xo","uploaded_at":"2014-04-12T00:07:24Z"},{"playlist":"PBL Apprentice | Spring 2014","title":"[IN] The Apprentice - Finance, Part 2 (Spring 2014)","unique_id":"R-C1VwObKhU","uploaded_at":"2014-04-12T00:36:15Z"},{"playlist":"PBL TV Season 7 | Fall 2013","title":"PBLTV Season 7 | Episode 1 - Food for All","unique_id":"3VCHUEVBuKQ","uploaded_at":"2013-10-21T02:57:25Z"},{"playlist":"PBL TV Season 7 | Fall 2013","title":"PBLTV Season 7 | Episode 2 - Johnny Holmes","unique_id":"Df0gdZspZ_c","uploaded_at":"2013-10-18T01:01:11Z"},{"playlist":"PBL TV Season 7 | Fall 2013","title":"PBLTV Season 7 | Episode 3 - PBL Chef America","unique_id":"8VFR7M8V270","uploaded_at":"2013-10-13T22:15:08Z"},{"playlist":"PBL TV Season 7 | Fall 2013","title":"PBLTV Season 7 | Episode 4 - Peace of Berkeley","unique_id":"hd2db_XSzqY","uploaded_at":"2013-11-28T01:56:39Z"},{"playlist":"PBL TV Season 7 | Fall 2013","title":"PBLTV Season 7 | Episode 5 - Solemate","unique_id":"iGIB1bK3-JQ","uploaded_at":"2013-11-27T11:53:49Z"},{"playlist":"PBL TV Season 7 | Fall 2013","title":"PBLTV Season 7 | Episode 6 - Historian 3rd Gen","unique_id":"2dCreZzF6Yw","uploaded_at":"2013-11-28T09:38:52Z"},{"playlist":"PBL TV Season 7 | Fall 2013","title":"PBLTV Season 7 | Episode 7 - Pickpockets","unique_id":"x7Ahfs7S6qY","uploaded_at":"2013-11-30T03:57:08Z"},{"playlist":"PBL Apprentice | Fall 2013","title":"[PBL][IN] The Apprentice: Marketing","unique_id":"3ttcvEvPTNY","uploaded_at":"2013-10-05T07:32:02Z"},{"playlist":"PBL Apprentice | Fall 2013","title":"[PBL][IN] The Apprentice: Consulting","unique_id":"IoeSpLRHUo4","uploaded_at":"2013-10-13T07:25:11Z"},{"playlist":"PBL Apprentice | Fall 2013","title":"[PBL][IN] The Apprentice: Marketing Challenge Recap","unique_id":"CA2fKZ9gBLo","uploaded_at":"2013-10-17T20:38:35Z"},{"playlist":"PBL Apprentice | Fall 2013","title":"[PBL][IN] The Apprentice: Historians","unique_id":"UBVbmHBgy2w","uploaded_at":"2013-10-19T05:47:53Z"},{"playlist":"PBL Apprentice | Fall 2013","title":"[PBL][IN] The Apprentice: Update #2","unique_id":"1-Sn_U4TtMM","uploaded_at":"2013-10-21T04:04:13Z"},{"playlist":"PBL Apprentice | Fall 2013","title":"[PBL][IN] Apprentice: Social","unique_id":"u-fxMVawIWI","uploaded_at":"2013-11-09T05:46:34Z"},{"playlist":"PBL Apprentice | Fall 2013","title":"[PBL][IN] Apprentice: Publications","unique_id":"5Du94zN5LXo","uploaded_at":"2013-11-09T06:39:29Z"},{"playlist":"PBL Apprentice | Fall 2013","title":"[PBL][IN] The Apprentice: Community Service","unique_id":"vDrzn7J2Pws","uploaded_at":"2013-11-17T06:25:07Z"},{"playlist":"PBL Apprentice | Fall 2013","title":"[PBL][IN] The Apprentice: Professional Development","unique_id":"Qsb7jS30-HA","uploaded_at":"2013-11-17T06:35:31Z"},{"playlist":"PBL Apprentice | Fall 2013","title":"[PBL][IN] The Apprentice: Executives","unique_id":"XcCHhFIzWhk","uploaded_at":"2013-12-03T08:40:45Z"},{"playlist":"3rd Gen | Fall 2013","title":"[PBL] Third General Meeting Video Fall 2013: Publications","unique_id":"_j-fwAyeL18","uploaded_at":"2013-11-01T20:54:21Z"},{"playlist":"3rd Gen | Fall 2013","title":"[PBL] Third General Meeting Video Fall 2013: Execs","unique_id":"Mxd8mi31hH8","uploaded_at":"2013-11-02T08:28:39Z"},{"playlist":"3rd Gen | Fall 2013","title":"[PBL] Third General Meeting Video Fall 2013: Consulting","unique_id":"iDAM0h677ag","uploaded_at":"2013-11-01T19:44:19Z"},{"playlist":"3rd Gen | Fall 2013","title":"Third General Meeting Fall 2013: Professional","unique_id":"ewUcskQnu5Q","uploaded_at":"2013-11-03T04:54:19Z"},{"playlist":"3rd Gen | Fall 2013","title":"[PBL] Third General Meeting Videos Fall 2013: Social","unique_id":"QihVmEXpA_s","uploaded_at":"2013-11-01T20:26:22Z"},{"playlist":"3rd Gen | Fall 2013","title":"[PBL] Third General Meeting Video Fall 2013: Finance","unique_id":"AZwP1MdAGkI","uploaded_at":"2013-11-02T23:35:32Z"},{"playlist":"3rd Gen | Fall 2013","title":"[PBL] Third General Meeting Videos Fall 2013: Internal Networking","unique_id":"yGLtMtE9MtM","uploaded_at":"2013-11-03T20:53:03Z"},{"playlist":"3rd Gen | Fall 2013","title":"[PBL] Third General Meeting Fall 2013: Marketing","unique_id":"IFwPEDTrE1Y","uploaded_at":"2013-11-03T05:45:39Z"},{"playlist":"3rd Gen | Fall 2013","title":"[PBL] Third General Meeting Fall 2013: Bloopers","unique_id":"oTem7-qtLLE","uploaded_at":"2013-11-03T06:00:23Z"},{"playlist":"3rd Gen | Fall 2013","title":"[PBL] Third General Meeting Videos Fall 2013: Community Service","unique_id":"xhGvzp_29vo","uploaded_at":"2013-11-05T05:48:05Z"},{"playlist":"The S Factor Performances | Spring 2013","title":"The S Factor: Publications","unique_id":"EgMw5vC1ZKs","uploaded_at":"2013-04-30T12:36:11Z"},{"playlist":"The S Factor Performances | Spring 2013","title":"The S Factor: Executives","unique_id":"HdB7BOid8wE","uploaded_at":"2013-04-30T11:59:43Z"},{"playlist":"The S Factor Performances | Spring 2013","title":"The S Factor: Community Service","unique_id":"ng9Y3Snrfts","uploaded_at":"2013-04-27T18:28:06Z"},{"playlist":"PBL Professional Workshops | Spring 2013","title":"[EX] PBL Spring 2013 Professional Day Workshop - General","unique_id":"NEoE2Ib3_w0","uploaded_at":"2013-02-20T06:32:06Z"},{"playlist":"PBL Professional Workshops | Spring 2013","title":"[PD] PBL Spring 2013 Professional Day Workshop - Professional Development","unique_id":"_Q3DXrmVFoo","uploaded_at":"2013-02-20T06:20:10Z"},{"playlist":"PBL Professional Workshops | Spring 2013","title":"[CO] PBL Spring 2013 Professional Day Workshop - Consulting","unique_id":"80mYaqBSXlI","uploaded_at":"2013-02-20T06:03:46Z"},{"playlist":"PBL Professional Workshops | Spring 2013","title":"[FI] PBL Spring 2013 Professional Day Workshop - Finance","unique_id":"kaL2GlNIjXY","uploaded_at":"2013-02-20T05:44:44Z"},{"playlist":"PBL Professional Workshops | Spring 2013","title":"[SO] PBL Spring 2013 Professional Day Workshop - Social","unique_id":"RotLal6KxWc","uploaded_at":"2013-02-20T05:23:46Z"},{"playlist":"PBL Professional Workshops | Spring 2013","title":"[MK] Spring 2013 Professional Day Workshop - Marketing","unique_id":"9sNA7ud5mqg","uploaded_at":"2013-02-20T05:13:59Z"},{"playlist":"PBL TV Season 6 | Spring 2013","title":"PBLtv S6E2: PBL Trash","unique_id":"nU5EkGHsFwY","uploaded_at":"2013-04-25T07:33:46Z"},{"playlist":"PBL TV Season 6 | Spring 2013","title":"[PBLtv] S6E1: TWTS1E1","unique_id":"fULOtp_tctQ","uploaded_at":"2013-03-25T07:41:19Z"},{"playlist":"PBL TV Season 6 | Spring 2013","title":"PBLtv Season 6 Preview","unique_id":"c2b81EtxMFc","uploaded_at":"2013-02-14T07:24:20Z"},{"playlist":"3rd Gen | Spring 2013","title":"[PBL] The Force WithIN","unique_id":"I-AMj5SmDiw","uploaded_at":"2013-04-25T15:06:36Z"},{"playlist":"3rd Gen | Spring 2013","title":"[PBL] Mjango Unashamed","unique_id":"zel-dPj11a4","uploaded_at":"2013-04-20T07:45:53Z"},{"playlist":"3rd Gen | Spring 2013","title":"[PBL] The League of CS","unique_id":"i4FaeOA2ByU","uploaded_at":"2013-04-17T19:41:49Z"},{"playlist":"3rd Gen | Spring 2013","title":"[PBL] Dan Dan","unique_id":"NOjq0lAzSDM","uploaded_at":"2013-04-21T07:50:55Z"},{"playlist":"3rd Gen | Spring 2013","title":"[PBL] Marketing Spring 2013: Achalkalypse","unique_id":"xujfqWzVi1k","uploaded_at":"2013-04-11T20:40:31Z"},{"playlist":"3rd Gen | Spring 2013","title":"[PBL] Professional Development Third Gen Spring 2013","unique_id":"2d3C0XrQWm8","uploaded_at":"2013-04-17T19:19:51Z"},{"playlist":"3rd Gen | Spring 2013","title":"[PBL] The Finance Five","unique_id":"NWkRwT7H6r4","uploaded_at":"2013-04-09T02:01:11Z"},{"playlist":"Social Mixer | Spring 2012","title":"[PBL] First Gen Social Video","unique_id":"D2-hDzkr-WY","uploaded_at":"2012-09-01T04:39:47Z"},{"playlist":"Social Mixer | Spring 2012","title":"[PBL] Fall 2012 First Gen Officer Intro Video","unique_id":"vgv8gWxdb-g","uploaded_at":"2012-09-01T04:40:00Z"},{"playlist":"Social Mixer | Spring 2012","title":"[PBL] Spring 2012 Recap","unique_id":"3HDM1eLz9AA","uploaded_at":"2012-05-01T03:44:39Z"},{"playlist":"Social Mixer | Spring 2012","title":"[HT] Spring 2012 3rd Gen - Finding Dreams","unique_id":"cai7_R4GBwQ","uploaded_at":"2012-04-11T19:38:01Z"},{"playlist":"Social Mixer | Spring 2012","title":"PBL Spring 2012 Officers Introduction","unique_id":"gQ__BeGhU1Y","uploaded_at":"2012-02-06T22:57:18Z"},{"playlist":"Social Mixer | Spring 2012","title":"PBLtv 2011 Fall S3E1.avi","unique_id":"RlHmrIVeR8c","uploaded_at":"2011-09-30T18:18:09Z"},{"playlist":"Social Mixer | Spring 2012","title":"Fall 2011First Gen Officer Intro.avi","unique_id":"hn56kEeU48c","uploaded_at":"2011-09-02T23:47:38Z"},{"playlist":"Social Mixer | Spring 2012","title":"[PBLtv] S2E6: Calvin and Hobbes","unique_id":"lF6tdBKxQk8","uploaded_at":"2011-04-05T06:17:28Z"},{"playlist":"Banquet | Spring 2012","title":"[PBL] Spring 2012 Recap","unique_id":"3HDM1eLz9AA","uploaded_at":"2012-05-01T03:44:39Z"},{"playlist":"Banquet | Spring 2012","title":"[PBL] Consulting Banquet Spring 2012","unique_id":"EDVWCHLHDWc","uploaded_at":"2012-05-01T06:27:30Z"},{"playlist":"Banquet | Spring 2012","title":"[PBL] Community Service Banquet Spring 2012","unique_id":"Mig2a5kqdus","uploaded_at":"2012-05-01T09:21:44Z"},{"playlist":"Banquet | Spring 2012","title":"[PBL] Exec Banquet Spring 2012","unique_id":"q2cbcD1nnwY","uploaded_at":"2012-05-01T10:47:34Z"},{"playlist":"Banquet | Spring 2012","title":"[PBL] Finance Banquet Spring 2012","unique_id":"iJVsfd77JBg","uploaded_at":"2012-05-01T11:00:43Z"},{"playlist":"Banquet | Spring 2012","title":"[PBL] Faculty Relations Banquet Spring 2012","unique_id":"oM1t2dQ7T-E","uploaded_at":"2012-05-01T12:42:26Z"},{"playlist":"Banquet | Spring 2012","title":"[PBL] Internal Networking Banquet Spring 2012","unique_id":"LoRtChwFi5c","uploaded_at":"2012-05-01T13:54:02Z"},{"playlist":"Banquet | Spring 2012","title":"[PBL] Marketing Banquet Spring 2012","unique_id":"Xk-ElmRX8l0","uploaded_at":"2012-05-01T16:02:15Z"},{"playlist":"Banquet | Spring 2012","title":"[PBL] Professional Development Banquet Spring 2012","unique_id":"9KJLkei7PAY","uploaded_at":"2012-05-01T16:24:29Z"},{"playlist":"Banquet | Spring 2012","title":"[PBL] Publications Banquet Spring 2012","unique_id":"Ss7-8mpBiOU","uploaded_at":"2012-05-01T18:09:50Z"},{"playlist":"Banquet | Spring 2012","title":"[PBL][SO][SP12] Social Banquet Spring 2012","unique_id":"eMsYgikHvC4","uploaded_at":"2012-05-01T18:42:47Z"},{"playlist":"Banquet | Fall 2011","title":"[PBL] Exec Video Fall Banquet Video","unique_id":"N8UROqGBsik","uploaded_at":"2012-02-11T03:19:53Z"},{"playlist":"Banquet | Fall 2011","title":"[PBL] Consulting Fall 2011 Banquet Video","unique_id":"EPxfTRWAT0w","uploaded_at":"2012-02-10T23:38:43Z"},{"playlist":"Banquet | Fall 2011","title":"[PBL] Social - Banquet Video Fall 2011 - Sunset Blvd","unique_id":"JPgYW96-VQo","uploaded_at":"2011-12-11T01:43:24Z"},{"playlist":"Banquet | Fall 2011","title":"[PBL] Community Service - Fall 2011 Banquet Video","unique_id":"sX0AADLn1FM","uploaded_at":"2011-12-10T21:03:37Z"},{"playlist":"Banquet | Fall 2011","title":"[PBL] Marketing - Fall 2011 Banquet Video","unique_id":"oAO1PsjAIaY","uploaded_at":"2011-12-08T02:31:11Z"},{"playlist":"Social's Committee Royale | Spring 2010","title":"[PBL] Committee Royale Sp 10 - Introductions","unique_id":"4CgInjNrZhg","uploaded_at":"2010-04-19T02:04:16Z"},{"playlist":"Social's Committee Royale | Spring 2010","title":"[PBL] Committee Royale Sp 10 - Cross Dressing","unique_id":"H6wwBK3Binc","uploaded_at":"2010-04-19T03:21:18Z"},{"playlist":"Social's Committee Royale | Spring 2010","title":"[PBL] Committee Royale Sp 10 - BizTech (Talent)","unique_id":"CJ3hcZ92dZg","uploaded_at":"2010-04-18T22:40:44Z"},{"playlist":"Social's Committee Royale | Spring 2010","title":"[PBL] Committee Royale Sp 10 - Community Service (Talent)","unique_id":"eQ9xB2Zy7HE","uploaded_at":"2010-04-18T22:49:05Z"},{"playlist":"Social's Committee Royale | Spring 2010","title":"[PBL] Committee Royale Sp 10 - Execs/inGroup (Talent)","unique_id":"lrTOuOQ9u_4","uploaded_at":"2010-04-18T23:01:15Z"},{"playlist":"Social's Committee Royale | Spring 2010","title":"[PBL] Committee Royale Sp 10 - Faculty Relations P1 (Talent)","unique_id":"0JR0-t1lrJE","uploaded_at":"2010-04-18T23:13:16Z"},{"playlist":"Social's Committee Royale | Spring 2010","title":"[PBL] Committee Royale Sp 10 - Faculty Relations P2 (Talent)","unique_id":"CYV_NbtWGK4","uploaded_at":"2010-04-18T23:18:33Z"},{"playlist":"Social's Committee Royale | Spring 2010","title":"[PBL] Committee Royale Sp 10 - Finance (Talent)","unique_id":"3C0AF_sZYwQ","uploaded_at":"2010-04-18T23:22:16Z"},{"playlist":"Social's Committee Royale | Spring 2010","title":"[PBL] Committee Royale Sp 10 - Historian (Talent)","unique_id":"BTUmGdTEFMc","uploaded_at":"2010-04-18T23:33:08Z"},{"playlist":"Social's Committee Royale | Spring 2010","title":"[PBL] Committee Royale Sp 10 - Marketing (Talent)","unique_id":"HadHrduKgFU","uploaded_at":"2010-04-18T23:40:58Z"},{"playlist":"Social's Committee Royale | Spring 2010","title":"[PBL] Committee Royale Sp 10 - Professional Development (Talent)","unique_id":"xRYZz5mnvwo","uploaded_at":"2010-04-19T03:07:49Z"},{"playlist":"Social's Committee Royale | Spring 2010","title":"[PBL] Committee Royale Sp 10 - Publications (Talent)","unique_id":"51yN4DmAbsk","uploaded_at":"2010-04-18T23:49:38Z"},{"playlist":"Favorites","title":"[Berkeley PBL] First General Meeting Officer Introduction Video Fall 2009","unique_id":"RVXFDtvu8-o","uploaded_at":"2009-09-02T08:03:36Z"},{"playlist":"Favorites","title":"[PBL] First Gen Video - The Exec Team","unique_id":"Vg1ANR0bIAc","uploaded_at":"2010-02-12T00:37:47Z"},{"playlist":"Favorites","title":"[PBL] First Gen Officer Team Video","unique_id":"LdrG_8BB-TE","uploaded_at":"2010-02-12T00:41:10Z"}]